mime_enum/__init__.py
mime_enum/core.py
mime_enum/mimetype.py
mime_enum/scripts/generate_mimetypes.py
mime_enum-0.0.1.dist-info/METADATA
mime_enum-0.0.1.dist-info/WHEEL
mime_enum-0.0.1.dist-info/licenses/LICENSE
mime_enum-0.0.1.dist-info/RECORD
