Metadata-Version: 2.4
Name: mime-enum
Version: 0.0.1
Summary: Type-safe MIME type enumeration for Python
Project-URL: Homepage, https://github.com/fpgmaas/mime-enum
Project-URL: Repository, https://github.com/fpgmaas/mime-enum
Project-URL: Documentation, https://fpgmaas.github.io/mime-enum/
Author-email: Florian Maas <fpgmaas@gmail.com>
License-File: LICENSE
Keywords: content-type,enum,file-extension,mime,mime-type
Classifier: Intended Audience :: Developers
Classifier: Programming Language :: Python
Classifier: Programming Language :: Python :: 3
Classifier: Programming Language :: Python :: 3.11
Classifier: Programming Language :: Python :: 3.12
Classifier: Programming Language :: Python :: 3.13
Classifier: Topic :: Software Development :: Libraries :: Python Modules
Requires-Python: <4.0,>=3.11
